{
  "filename": "smart_tree_system.json",
  "case": "E",
  "keywords": [
    {
      "word": "수경삽목시스템으로 수종별",
      "score": 0.614
    },
    {
      "word": "식물생육지수",
      "score": 0.61
    },
    {
      "word": "대표특허 수목진단기",
      "score": 0.606
    },
    {
      "word": "식물생육지수 적용",
      "score": 0.606
    },
    {
      "word": "식물생육지수 상태",
      "score": 0.605
    },
    {
      "word": "촉진형 수경삽목시스템",
      "score": 0.6
    },
    {
      "word": "필요 식물생육지수",
      "score": 0.598
    },
    {
      "word": "유형 제품설계",
      "score": 0.596
    },
    {
      "word": "통해 생육이",
      "score": 0.594
    },
    {
      "word": "기반 생육",
      "score": 0.591
    }
  ]
}