{
  "filename": "info_total_service.json",
  "case": "F",
  "keywords": [
    {
      "word": "인프라 분야의 dx",
      "score": 0.719
    },
    {
      "word": "스마트 인프라 기술",
      "score": 0.68
    },
    {
      "word": "프라 기술 구현을",
      "score": 0.676
    },
    {
      "word": "인프라 정보 자동",
      "score": 0.675
    },
    {
      "word": "인프라 기반의",
      "score": 0.652
    },
    {
      "word": "도시 인프라 정보",
      "score": 0.632
    },
    {
      "word": "컨셉디자인 인프라 정보",
      "score": 0.628
    },
    {
      "word": "마킹 툴킷장치 인프라",
      "score": 0.621
    },
    {
      "word": "중심의 스마트 프라",
      "score": 0.613
    },
    {
      "word": "기술을 활용하 도시",
      "score": 0.594
    }
  ]
}