{
  "filename": "smart_skincare_machine.json",
  "case": "F",
  "keywords": [
    {
      "word": "기술보유자 삼육대학교 구분",
      "score": 0.663
    },
    {
      "word": "삼육대학교 구분 발명의",
      "score": 0.638
    },
    {
      "word": "혁신실험실은",
      "score": 0.635
    },
    {
      "word": "기술 기술이전 성능검토",
      "score": 0.591
    },
    {
      "word": "아이디어 기술 기술이전",
      "score": 0.572
    },
    {
      "word": "있는 의료기기 컨셉디자인",
      "score": 0.542
    },
    {
      "word": "유형 제품설계",
      "score": 0.522
    },
    {
      "word": "설계 개발 시작품",
      "score": 0.521
    },
    {
      "word": "광조사부를 개발",
      "score": 0.517
    },
    {
      "word": "개발 구분 제품",
      "score": 0.515
    }
  ]
}